{"version":1,"tile":"9/454/204","count":1,"reports":[{"id":"weathernews4459","name":"大津波警報発令により、海岸付近の都道が通行止めになりました。 今朝、通行止めは解除になりましたが、海岸付近には近づかないように自治体の放送あり。 03-12 0...","text":"大津波警報発令により、海岸付近の都道が通行止めになりました。 今朝、通行止めは解除になりましたが、海岸付近には近づかないように自治体の放送あり。 03-12 09:51:31","label":"大津波警報発令により、海岸付近の都道が通行止めになりました。 今朝、通行止めは解...","desc":"<p class=\"tweettext\">大津波警報発令により、海岸付近の都道が通行止めになりました。  今朝、通行止めは解除になりましたが、海岸付近には近づかないように自治体の放送あり。</p><p class=\"time\">03-12 09:51:31</p>","lon":139.47623,"lat":34.06613,"img":"megaphone.png"}]}