{"version":1,"tile":"9/451/201","count":6,"reports":[{"id":"weathernews253","name":"長ーく、いつまでもーな感じで揺れてました・・ 03-12 02:00:48","text":"長ーく、いつまでもーな感じで揺れてました・・ 03-12 02:00:48","desc":"<p class=\"tweettext\">長ーく、いつまでもーな感じで揺れてました・・</p><p class=\"time\">03-12 02:00:48</p>","lon":137.8056,"lat":35.49216,"img":"megaphone.png"},{"id":"weathernews5953","name":"被害は無いです。けど、１９号線はトラックが多いです。御気をつけて。 03-12 13:24:32","text":"被害は無いです。けど、１９号線はトラックが多いです。御気をつけて。 03-12 13:24:32","desc":"<p class=\"tweettext\">被害は無いです。けど、１９号線はトラックが多いです。御気をつけて。</p><p class=\"time\">03-12 13:24:32</p>","lon":137.49918,"lat":35.47389,"img":"megaphone.png"},{"id":"weathernews6266","name":"地震が起きた時は車載リフトの上に居ました。最初は風かと思いましたが、電線が揺れているのと車載キャリアカーの明らかな揺れから地震だと分かりました。発表では震度４の...","text":"地震が起きた時は車載リフトの上に居ました。最初は風かと思いましたが、電線が揺れているのと車載キャリアカーの明らかな揺れから地震だと分かりました。発表では震度４の地域ですが、軽い船酔いの状態になりました。携帯は暫くして不通になりました。他には目立った被害はありません 03-12 13:42:59","desc":"<p class=\"tweettext\">地震が起きた時は車載リフトの上に居ました。最初は風かと思いましたが、電線が揺れているのと車載キャリアカーの明らかな揺れから地震だと分かりました。発表では震度４の地域ですが、軽い船酔いの状態になりました。携帯は暫くして不通になりました。他には目立った被害はありません</p><p class=\"time\">03-12 13:42:59</p>","lon":137.78346,"lat":35.48757,"img":"megaphone.png"},{"id":"weathernews7513","name":"こちらは被害は有りませんが、市でも救援対策本部の設置や、医師、看護師、薬剤師などの派遣、消防職員、水道職員も応援要請に対応できるよう待機してるみたいです。 03...","text":"こちらは被害は有りませんが、市でも救援対策本部の設置や、医師、看護師、薬剤師などの派遣、消防職員、水道職員も応援要請に対応できるよう待機してるみたいです。 03-12 15:17:27","desc":"<p class=\"tweettext\">こちらは被害は有りませんが、市でも救援対策本部の設置や、医師、看護師、薬剤師などの派遣、消防職員、水道職員も応援要請に対応できるよう待機してるみたいです。</p><p class=\"time\">03-12 15:17:27</p>","lon":137.47833,"lat":35.48215,"img":"megaphone.png"},{"id":"weathernews7778","name":"特に被害はありません揺れも今のところ強い揺れは感じません 03-12 15:56:47","text":"特に被害はありません揺れも今のところ強い揺れは感じません 03-12 15:56:47","desc":"<p class=\"tweettext\">特に被害はありません揺れも今のところ強い揺れは感じません</p><p class=\"time\">03-12 15:56:47</p>","lon":137.4859,"lat":35.49075,"img":"megaphone.png"},{"id":"weathernews7873","name":"被害なし 03-12 16:09:13","text":"被害なし 03-12 16:09:13","desc":"<p class=\"tweettext\">被害なし</p><p class=\"time\">03-12 16:09:13</p>","lon":137.65598,"lat":35.68603,"img":"megaphone.png"}]}